sphinx_cea_theme/__init__.py
sphinx_cea_theme/footer.html
sphinx_cea_theme/layout.html
sphinx_cea_theme/theme.conf
sphinx_cea_theme/static/css/sphinx_cea_theme.css
sphinx_cea_theme/static/img/cea-logo.svg
sphinx_cea_theme-1.0.0.dist-info/LICENSE.md
sphinx_cea_theme-1.0.0.dist-info/METADATA
sphinx_cea_theme-1.0.0.dist-info/WHEEL
sphinx_cea_theme-1.0.0.dist-info/entry_points.txt
sphinx_cea_theme-1.0.0.dist-info/top_level.txt
sphinx_cea_theme-1.0.0.dist-info/RECORD
