Metadata-Version: 2.1
Name: sphinx-cea-theme
Version: 1.0.0
Summary: CEA Docs theme for Sphinx
Home-page: https://cnrgh.gitlab.fr/lbi/sphinx_cea_theme/
Author: LBI team
Author-email: bioinfo@cnrgh.fr
License: CeCCIL
Platform: UNKNOWN
Classifier: Framework :: Sphinx
Classifier: Framework :: Sphinx :: Theme
Classifier: Development Status :: 5 - Production/Stable
Classifier: License :: OSI Approved :: CEA CNRS Inria Logiciel Libre License, version 2.1 (CeCILL-2.1)
Classifier: Environment :: Console
Classifier: Environment :: Web Environment
Classifier: Intended Audience :: Developers
Classifier: Programming Language :: Python :: 3
Classifier: Programming Language :: Python :: 3.3
Classifier: Programming Language :: Python :: 3.4
Classifier: Programming Language :: Python :: 3.5
Classifier: Programming Language :: Python :: 3.6
Classifier: Operating System :: OS Independent
Classifier: Topic :: Documentation
Classifier: Topic :: Software Development :: Documentation
Requires-Dist: sphinx (>=2.3.0)
Requires-Dist: sphinx-rtd-theme (>=0.4.3)
Provides-Extra: dev
Requires-Dist: transifex-client ; extra == 'dev'
Requires-Dist: sphinxcontrib-httpdomain ; extra == 'dev'
